flask_postmark/__init__.py
flask_postmark/core.py
Flask_Postmark-0.3.1.dist-info/LICENSE
Flask_Postmark-0.3.1.dist-info/METADATA
Flask_Postmark-0.3.1.dist-info/WHEEL
Flask_Postmark-0.3.1.dist-info/top_level.txt
Flask_Postmark-0.3.1.dist-info/RECORD
