Metadata-Version: 2.1
Name: Flask-Postmark
Version: 0.3.1
Summary: Postmark Flask extension
Home-page: https://github.com/Stranger6667/Flask-Postmark
Author: Dmitry Dygalo
Author-email: dadygalo@gmail.com
License: MIT
Keywords: flask,postmark,email
Platform: any
Classifier: Development Status :: 4 - Beta
Classifier: Environment :: Web Environment
Classifier: Intended Audience :: Developers
Classifier: License :: OSI Approved :: MIT License
Classifier: Operating System :: OS Independent
Classifier: Programming Language :: Python
Classifier: Programming Language :: Python :: 3.5
Classifier: Programming Language :: Python :: 3.6
Classifier: Programming Language :: Python :: 3.7
Classifier: Programming Language :: Python :: 3.8
Classifier: Programming Language :: Python :: 3.9
Classifier: Programming Language :: Python :: Implementation :: CPython
Classifier: Programming Language :: Python :: Implementation :: PyPy
Classifier: Topic :: Internet :: WWW/HTTP :: Dynamic Content
Classifier: Topic :: Software Development :: Libraries :: Python Modules
Classifier: Topic :: Communications :: Email
Requires-Dist: Flask
Requires-Dist: postmarker (>=0.11.2)
